{
  "ret": 200,
  "msg": "声音播放数据",
  "data": {
    "uid": 88178548,
    "albumId": 9723091,
    "sort": 0,
    "pageNum": 1,
    "pageSize": 30,
    "tracksAudioPlay": [
      {
        "index": 1,
        "trackId": 45982332,
        "trackName": "《人在江湖》郭德纲 于谦",
        "trackUrl": "/xiangsheng/9723091/45982332",
        "trackCoverPath": "//imagev2.xmcdn.com/group31/M07/0E/5B/wKgJX1mAQg2SWaYDAAAw0CICWi8444.jpg",
        "albumId": 9723091,
        "albumName": "郭德纲21年相声精选",
        "albumUrl": "/xiangsheng/9723091/",
        "anchorId": 1000202,
        "canPlay": true,
        "isBaiduMusic": false,
        "isPaid": false,
        "duration": 2076,
        "src": "http://aod.tx.xmcdn.com/group31/M0A/21/AD/wKgJSVmBkvOyNFPNAQA4-ZWCTvA299.m4a",
        "hasBuy": true,
        "albumIsSample": false,
        "sampleDuration": 0,
        "updateTime": "15天前",
        "createTime": "1年前",
        "isLike": true,
        "isCopyright": true,
        "firstPlayStatus": true
      },
      {
        "index": 2,
        "trackId": 45982336,
        "trackName": "《文史专家》 郭德纲 于谦",
        "trackUrl": "/xiangsheng/9723091/45982336",
        "trackCoverPath": "//imagev2.xmcdn.com/group31/M07/0E/5B/wKgJX1mAQg2SWaYDAAAw0CICWi8444.jpg",
        "albumId": 9723091,
        "albumName": "郭德纲21年相声精选",
        "albumUrl": "/xiangsheng/9723091/",
        "anchorId": 1000202,
        "canPlay": true,
        "isBaiduMusic": false,
        "isPaid": false,
        "duration": 2998,
        "src": "http://aod.tx.xmcdn.com/group30/M02/3F/25/wKgJXlmBkwnxTb8lAXIEB3_E0mE601.m4a",
        "hasBuy": true,
        "albumIsSample": false,
        "sampleDuration": 0,
        "updateTime": "1天前",
        "createTime": "1年前",
        "isLike": false,
        "isCopyright": true,
        "firstPlayStatus": true
      },
      {
        "index": 3,
        "trackId": 45982338,
        "trackName": "《学问家》 郭德纲 于谦",
        "trackUrl": "/xiangsheng/9723091/45982338",
        "trackCoverPath": "//imagev2.xmcdn.com/group31/M07/0E/5B/wKgJX1mAQg2SWaYDAAAw0CICWi8444.jpg",
        "albumId": 9723091,
        "albumName": "郭德纲21年相声精选",
        "albumUrl": "/xiangsheng/9723091/",
        "anchorId": 1000202,
        "canPlay": true,
        "isBaiduMusic": false,
        "isPaid": false,
        "duration": 1817,
        "src": "http://aod.tx.xmcdn.com/group31/M0A/21/AD/wKgJSVmBku_ANXULAOBNF_Mwy-o627.m4a",
        "hasBuy": true,
        "albumIsSample": false,
        "sampleDuration": 0,
        "updateTime": "2月前",
        "createTime": "1年前",
        "isLike": false,
        "isCopyright": true,
        "firstPlayStatus": true
      },
      {
        "index": 4,
        "trackId": 45982342,
        "trackName": "《一户侯》 郭德纲 于谦",
        "trackUrl": "/xiangsheng/9723091/45982342",
        "trackCoverPath": "//imagev2.xmcdn.com/group31/M07/0E/5B/wKgJX1mAQg2SWaYDAAAw0CICWi8444.jpg",
        "albumId": 9723091,
        "albumName": "郭德纲21年相声精选",
        "albumUrl": "/xiangsheng/9723091/",
        "anchorId": 1000202,
        "canPlay": true,
        "isBaiduMusic": false,
        "isPaid": false,
        "duration": 1914,
        "src": "http://audio.xmcdn.com/group30/M02/3F/24/wKgJXlmBkwCSsyRnAOw4HLy7JKU631.m4a",
        "hasBuy": true,
        "albumIsSample": false,
        "sampleDuration": 0,
        "updateTime": "28天前",
        "createTime": "1年前",
        "isLike": false,
        "isCopyright": true,
        "firstPlayStatus": true
      },
      {
        "index": 5,
        "trackId": 45982355,
        "trackName": "《败家子儿》 郭德纲 于谦",
        "trackUrl": "/xiangsheng/9723091/45982355",
        "trackCoverPath": "//imagev2.xmcdn.com/group31/M07/0E/5B/wKgJX1mAQg2SWaYDAAAw0CICWi8444.jpg",
        "albumId": 9723091,
        "albumName": "郭德纲21年相声精选",
        "albumUrl": "/xiangsheng/9723091/",
        "anchorId": 1000202,
        "canPlay": true,
        "isBaiduMusic": false,
        "isPaid": false,
        "duration": 1377,
        "src": "http://audio.xmcdn.com/group30/M02/3F/2A/wKgJXlmBkw2zg0LjAKntzSZLubI803.m4a",
        "hasBuy": true,
        "albumIsSample": false,
        "sampleDuration": 0,
        "updateTime": "28天前",
        "createTime": "1年前",
        "isLike": false,
        "isCopyright": true,
        "firstPlayStatus": true
      },
      {
        "index": 6,
        "trackId": 45982468,
        "trackName": "《拴娃娃》 郭德纲 于谦",
        "trackUrl": "/xiangsheng/9723091/45982468",
        "trackCoverPath": "//imagev2.xmcdn.com/group31/M07/0E/5B/wKgJX1mAQg2SWaYDAAAw0CICWi8444.jpg",
        "albumId": 9723091,
        "albumName": "郭德纲21年相声精选",
        "albumUrl": "/xiangsheng/9723091/",
        "anchorId": 1000202,
        "canPlay": true,
        "isBaiduMusic": false,
        "isPaid": false,
        "duration": 4578,
        "src": "http://audio.xmcdn.com/group30/M02/3F/2C/wKgJXlmBkyqCCGafAjTl3bXNRQY773.m4a",
        "hasBuy": true,
        "albumIsSample": false,
        "sampleDuration": 0,
        "updateTime": "28天前",
        "createTime": "1年前",
        "isLike": false,
        "isCopyright": true,
        "firstPlayStatus": true
      },
      {
        "index": 7,
        "trackId": 45982471,
        "trackName": "《吃论》郭德纲、于谦",
        "trackUrl": "/xiangsheng/9723091/45982471",
        "trackCoverPath": "//imagev2.xmcdn.com/group31/M07/0E/5B/wKgJX1mAQg2SWaYDAAAw0CICWi8444.jpg",
        "albumId": 9723091,
        "albumName": "郭德纲21年相声精选",
        "albumUrl": "/xiangsheng/9723091/",
        "anchorId": 1000202,
        "canPlay": true,
        "isBaiduMusic": false,
        "isPaid": false,
        "duration": 2177,
        "src": "http://audio.xmcdn.com/group31/M04/21/AD/wKgJSVmBkyPwNR9qAQyqHEOZg04653.m4a",
        "hasBuy": true,
        "albumIsSample": false,
        "sampleDuration": 0,
        "updateTime": "28天前",
        "createTime": "1年前",
        "isLike": false,
        "isCopyright": true,
        "firstPlayStatus": true
      },
      {
        "index": 8,
        "trackId": 45982512,
        "trackName": "《我要穿越》郭德纲 于谦",
        "trackUrl": "/xiangsheng/9723091/45982512",
        "trackCoverPath": "//imagev2.xmcdn.com/group31/M07/0E/5B/wKgJX1mAQg2SWaYDAAAw0CICWi8444.jpg",
        "albumId": 9723091,
        "albumName": "郭德纲21年相声精选",
        "albumUrl": "/xiangsheng/9723091/",
        "anchorId": 1000202,
        "canPlay": true,
        "isBaiduMusic": false,
        "isPaid": false,
        "duration": 4740,
        "src": "http://aod.tx.xmcdn.com/group30/M02/3F/2F/wKgJXlmBkzjBVKcJAkjreZWsQPw265.m4a",
        "hasBuy": true,
        "albumIsSample": false,
        "sampleDuration": 0,
        "updateTime": "1月前",
        "createTime": "1年前",
        "isLike": false,
        "isCopyright": true,
        "firstPlayStatus": true
      },
      {
        "index": 9,
        "trackId": 45982514,
        "trackName": "《大上寿》 郭德纲 于谦",
        "trackUrl": "/xiangsheng/9723091/45982514",
        "trackCoverPath": "//imagev2.xmcdn.com/group31/M07/0E/5B/wKgJX1mAQg2SWaYDAAAw0CICWi8444.jpg",
        "albumId": 9723091,
        "albumName": "郭德纲21年相声精选",
        "albumUrl": "/xiangsheng/9723091/",
        "anchorId": 1000202,
        "canPlay": true,
        "isBaiduMusic": false,
        "isPaid": false,
        "duration": 3346,
        "src": "http://audio.xmcdn.com/group30/M05/3F/34/wKgJXlmBk0rTzPOaAZzgU85XL08950.m4a",
        "hasBuy": true,
        "albumIsSample": false,
        "sampleDuration": 0,
        "updateTime": "28天前",
        "createTime": "1年前",
        "isLike": false,
        "isCopyright": true,
        "firstPlayStatus": true
      },
      {
        "index": 10,
        "trackId": 45982516,
        "trackName": "《独占花魁》 郭德纲 于谦",
        "trackUrl": "/xiangsheng/9723091/45982516",
        "trackCoverPath": "//imagev2.xmcdn.com/group31/M07/0E/5B/wKgJX1mAQg2SWaYDAAAw0CICWi8444.jpg",
        "albumId": 9723091,
        "albumName": "郭德纲21年相声精选",
        "albumUrl": "/xiangsheng/9723091/",
        "anchorId": 1000202,
        "canPlay": true,
        "isBaiduMusic": false,
        "isPaid": false,
        "duration": 1886,
        "src": "http://audio.xmcdn.com/group30/M05/3F/31/wKgJXlmBkzvjRMDEAOjSWWGNg6k515.m4a",
        "hasBuy": true,
        "albumIsSample": false,
        "sampleDuration": 0,
        "updateTime": "7月前",
        "createTime": "1年前",
        "isLike": false,
        "isCopyright": true,
        "firstPlayStatus": true
      },
      {
        "index": 11,
        "trackId": 45982519,
        "trackName": "《好好学习》 郭德纲 于谦",
        "trackUrl": "/xiangsheng/9723091/45982519",
        "trackCoverPath": "//imagev2.xmcdn.com/group31/M07/0E/5B/wKgJX1mAQg2SWaYDAAAw0CICWi8444.jpg",
        "albumId": 9723091,
        "albumName": "郭德纲21年相声精选",
        "albumUrl": "/xiangsheng/9723091/",
        "anchorId": 1000202,
        "canPlay": true,
        "isBaiduMusic": false,
        "isPaid": false,
        "duration": 2344,
        "src": "http://audio.xmcdn.com/group30/M05/3F/34/wKgJXlmBk0bCoUgQASFBhhhG5kM683.m4a",
        "hasBuy": true,
        "albumIsSample": false,
        "sampleDuration": 0,
        "updateTime": "28天前",
        "createTime": "1年前",
        "isLike": false,
        "isCopyright": true,
        "firstPlayStatus": true
      },
      {
        "index": 12,
        "trackId": 45982520,
        "trackName": "《健康生活》 郭德纲 于谦",
        "trackUrl": "/xiangsheng/9723091/45982520",
        "trackCoverPath": "//imagev2.xmcdn.com/group31/M07/0E/5B/wKgJX1mAQg2SWaYDAAAw0CICWi8444.jpg",
        "albumId": 9723091,
        "albumName": "郭德纲21年相声精选",
        "albumUrl": "/xiangsheng/9723091/",
        "anchorId": 1000202,
        "canPlay": true,
        "isBaiduMusic": false,
        "isPaid": false,
        "duration": 1201,
        "src": "http://audio.xmcdn.com/group30/M05/3F/37/wKgJXlmBk0XTGQLmAJRK4OT2hrc289.m4a",
        "hasBuy": true,
        "albumIsSample": false,
        "sampleDuration": 0,
        "updateTime": "28天前",
        "createTime": "1年前",
        "isLike": false,
        "isCopyright": true,
        "firstPlayStatus": true
      },
      {
        "index": 13,
        "trackId": 45982573,
        "trackName": "《叫卖图》 郭德纲 于谦",
        "trackUrl": "/xiangsheng/9723091/45982573",
        "trackCoverPath": "//imagev2.xmcdn.com/group31/M07/0E/5B/wKgJX1mAQg2SWaYDAAAw0CICWi8444.jpg",
        "albumId": 9723091,
        "albumName": "郭德纲21年相声精选",
        "albumUrl": "/xiangsheng/9723091/",
        "anchorId": 1000202,
        "canPlay": true,
        "isBaiduMusic": false,
        "isPaid": false,
        "duration": 1946,
        "src": "http://audio.xmcdn.com/group31/M07/21/B0/wKgJSVmBk2GhiOv4APA4FNNrJUg480.m4a",
        "hasBuy": true,
        "albumIsSample": false,
        "sampleDuration": 0,
        "updateTime": "28天前",
        "createTime": "1年前",
        "isLike": false,
        "isCopyright": true,
        "firstPlayStatus": true
      },
      {
        "index": 14,
        "trackId": 45982576,
        "trackName": "《老师来了》 郭德纲 于谦 高峰",
        "trackUrl": "/xiangsheng/9723091/45982576",
        "trackCoverPath": "//imagev2.xmcdn.com/group31/M07/0E/5B/wKgJX1mAQg2SWaYDAAAw0CICWi8444.jpg",
        "albumId": 9723091,
        "albumName": "郭德纲21年相声精选",
        "albumUrl": "/xiangsheng/9723091/",
        "anchorId": 1000202,
        "canPlay": true,
        "isBaiduMusic": false,
        "isPaid": false,
        "duration": 1902,
        "src": "http://audio.xmcdn.com/group31/M07/21/B2/wKgJSVmBk2niO8BcAOq6uU-IJ_w562.m4a",
        "hasBuy": true,
        "albumIsSample": false,
        "sampleDuration": 0,
        "updateTime": "28天前",
        "createTime": "1年前",
        "isLike": false,
        "isCopyright": true,
        "firstPlayStatus": true
      },
      {
        "index": 15,
        "trackId": 45982634,
        "trackName": "《朋友论》 郭德纲 于谦",
        "trackUrl": "/xiangsheng/9723091/45982634",
        "trackCoverPath": "//imagev2.xmcdn.com/group31/M07/0E/5B/wKgJX1mAQg2SWaYDAAAw0CICWi8444.jpg",
        "albumId": 9723091,
        "albumName": "郭德纲21年相声精选",
        "albumUrl": "/xiangsheng/9723091/",
        "anchorId": 1000202,
        "canPlay": true,
        "isBaiduMusic": false,
        "isPaid": false,
        "duration": 2473,
        "src": "http://aod.tx.xmcdn.com/group31/M00/21/90/wKgJX1mBk4KAuEbeATE49WFNXhU819.m4a",
        "hasBuy": true,
        "albumIsSample": false,
        "sampleDuration": 0,
        "updateTime": "28天前",
        "createTime": "1年前",
        "isLike": false,
        "isCopyright": true,
        "firstPlayStatus": true
      },
      {
        "index": 16,
        "trackId": 45982638,
        "trackName": "《瞧这一家子》 郭德纲 于谦",
        "trackUrl": "/xiangsheng/9723091/45982638",
        "trackCoverPath": "//imagev2.xmcdn.com/group31/M07/0E/5B/wKgJX1mAQg2SWaYDAAAw0CICWi8444.jpg",
        "albumId": 9723091,
        "albumName": "郭德纲21年相声精选",
        "albumUrl": "/xiangsheng/9723091/",
        "anchorId": 1000202,
        "canPlay": true,
        "isBaiduMusic": false,
        "isPaid": false,
        "duration": 2166,
        "src": "http://aod.tx.xmcdn.com/group31/M00/21/90/wKgJX1mBk4CTK_jKAQtYMGeVME4224.m4a",
        "hasBuy": true,
        "albumIsSample": false,
        "sampleDuration": 0,
        "updateTime": "28天前",
        "createTime": "1年前",
        "isLike": false,
        "isCopyright": true,
        "firstPlayStatus": true
      },
      {
        "index": 17,
        "trackId": 45982639,
        "trackName": "《怯富贵》 郭德纲 于谦",
        "trackUrl": "/xiangsheng/9723091/45982639",
        "trackCoverPath": "//imagev2.xmcdn.com/group31/M07/0E/5B/wKgJX1mAQg2SWaYDAAAw0CICWi8444.jpg",
        "albumId": 9723091,
        "albumName": "郭德纲21年相声精选",
        "albumUrl": "/xiangsheng/9723091/",
        "anchorId": 1000202,
        "canPlay": true,
        "isBaiduMusic": false,
        "isPaid": false,
        "duration": 2245,
        "src": "http://audio.xmcdn.com/group31/M00/21/93/wKgJX1mBk5uisCN6ARUZGpfUCIk519.m4a",
        "hasBuy": true,
        "albumIsSample": false,
        "sampleDuration": 0,
        "updateTime": "1年前",
        "createTime": "1年前",
        "isLike": false,
        "isCopyright": true,
        "firstPlayStatus": true
      },
      {
        "index": 18,
        "trackId": 45982643,
        "trackName": "《群八扇》郭德纲 于谦",
        "trackUrl": "/xiangsheng/9723091/45982643",
        "trackCoverPath": "//imagev2.xmcdn.com/group31/M07/0E/5B/wKgJX1mAQg2SWaYDAAAw0CICWi8444.jpg",
        "albumId": 9723091,
        "albumName": "郭德纲21年相声精选",
        "albumUrl": "/xiangsheng/9723091/",
        "anchorId": 1000202,
        "canPlay": true,
        "isBaiduMusic": false,
        "isPaid": false,
        "duration": 1795,
        "src": "http://audio.xmcdn.com/group31/M07/21/B8/wKgJSVmBk57C9dmVAN2egEd-gFc108.m4a",
        "hasBuy": true,
        "albumIsSample": false,
        "sampleDuration": 0,
        "updateTime": "1年前",
        "createTime": "1年前",
        "isLike": false,
        "isCopyright": true,
        "firstPlayStatus": true
      },
      {
        "index": 19,
        "trackId": 45982697,
        "trackName": "《卖五器》 郭德纲 于谦",
        "trackUrl": "/xiangsheng/9723091/45982697",
        "trackCoverPath": "//imagev2.xmcdn.com/group31/M07/0E/5B/wKgJX1mAQg2SWaYDAAAw0CICWi8444.jpg",
        "albumId": 9723091,
        "albumName": "郭德纲21年相声精选",
        "albumUrl": "/xiangsheng/9723091/",
        "anchorId": 1000202,
        "canPlay": true,
        "isBaiduMusic": false,
        "isPaid": false,
        "duration": 4610,
        "src": "http://aod.tx.xmcdn.com/group31/M07/21/B8/wKgJSVmBk7XxQHvvAjjePMnrplA740.m4a",
        "hasBuy": true,
        "albumIsSample": false,
        "sampleDuration": 0,
        "updateTime": "1年前",
        "createTime": "1年前",
        "isLike": false,
        "isCopyright": true,
        "firstPlayStatus": true
      },
      {
        "index": 20,
        "trackId": 45982741,
        "trackName": "《扒马褂》郭德纲 于谦 烧饼",
        "trackUrl": "/xiangsheng/9723091/45982741",
        "trackCoverPath": "//imagev2.xmcdn.com/group31/M07/0E/5B/wKgJX1mAQg2SWaYDAAAw0CICWi8444.jpg",
        "albumId": 9723091,
        "albumName": "郭德纲21年相声精选",
        "albumUrl": "/xiangsheng/9723091/",
        "anchorId": 1000202,
        "canPlay": true,
        "isBaiduMusic": false,
        "isPaid": false,
        "duration": 2861,
        "src": "http://audio.xmcdn.com/group30/M03/3F/44/wKgJXlmBk8rwBnakAWEOdxN9EbQ407.m4a",
        "hasBuy": true,
        "albumIsSample": false,
        "sampleDuration": 0,
        "updateTime": "1年前",
        "createTime": "1年前",
        "isLike": false,
        "isCopyright": true,
        "firstPlayStatus": true
      },
      {
        "index": 21,
        "trackId": 45982775,
        "trackName": "《扒马褂》 郭德纲 于谦 张鹤伦",
        "trackUrl": "/xiangsheng/9723091/45982775",
        "trackCoverPath": "//imagev2.xmcdn.com/group31/M07/0E/5B/wKgJX1mAQg2SWaYDAAAw0CICWi8444.jpg",
        "albumId": 9723091,
        "albumName": "郭德纲21年相声精选",
        "albumUrl": "/xiangsheng/9723091/",
        "anchorId": 1000202,
        "canPlay": true,
        "isBaiduMusic": false,
        "isPaid": false,
        "duration": 3761,
        "src": "http://audio.xmcdn.com/group30/M03/3F/47/wKgJXlmBk93j3r37AdAjApB0uOU068.m4a",
        "hasBuy": true,
        "albumIsSample": false,
        "sampleDuration": 0,
        "updateTime": "1年前",
        "createTime": "1年前",
        "isLike": false,
        "isCopyright": true,
        "firstPlayStatus": true
      },
      {
        "index": 22,
        "trackId": 45982777,
        "trackName": "《白事会》郭德纲 于谦",
        "trackUrl": "/xiangsheng/9723091/45982777",
        "trackCoverPath": "//imagev2.xmcdn.com/group31/M07/0E/5B/wKgJX1mAQg2SWaYDAAAw0CICWi8444.jpg",
        "albumId": 9723091,
        "albumName": "郭德纲21年相声精选",
        "albumUrl": "/xiangsheng/9723091/",
        "anchorId": 1000202,
        "canPlay": true,
        "isBaiduMusic": false,
        "isPaid": false,
        "duration": 3808,
        "src": "http://audio.xmcdn.com/group31/M01/21/BB/wKgJSVmBk_HTmsubAdX2pZHrk1E610.m4a",
        "hasBuy": true,
        "albumIsSample": false,
        "sampleDuration": 0,
        "updateTime": "1年前",
        "createTime": "1年前",
        "isLike": false,
        "isCopyright": true,
        "firstPlayStatus": true
      },
      {
        "index": 23,
        "trackId": 45982779,
        "trackName": "《你有病啊》郭德纲 于谦",
        "trackUrl": "/xiangsheng/9723091/45982779",
        "trackCoverPath": "//imagev2.xmcdn.com/group31/M07/0E/5B/wKgJX1mAQg2SWaYDAAAw0CICWi8444.jpg",
        "albumId": 9723091,
        "albumName": "郭德纲21年相声精选",
        "albumUrl": "/xiangsheng/9723091/",
        "anchorId": 1000202,
        "canPlay": true,
        "isBaiduMusic": false,
        "isPaid": false,
        "duration": 1664,
        "src": "http://audio.xmcdn.com/group31/M06/21/BE/wKgJSVmBk_iCEkkPAM1aIfbZhns104.m4a",
        "hasBuy": true,
        "albumIsSample": false,
        "sampleDuration": 0,
        "updateTime": "2月前",
        "createTime": "1年前",
        "isLike": false,
        "isCopyright": true,
        "firstPlayStatus": true
      },
      {
        "index": 24,
        "trackId": 45982828,
        "trackName": "《你这半辈子》郭德纲 于谦",
        "trackUrl": "/xiangsheng/9723091/45982828",
        "trackCoverPath": "//imagev2.xmcdn.com/group31/M07/0E/5B/wKgJX1mAQg2SWaYDAAAw0CICWi8444.jpg",
        "albumId": 9723091,
        "albumName": "郭德纲21年相声精选",
        "albumUrl": "/xiangsheng/9723091/",
        "anchorId": 1000202,
        "canPlay": true,
        "isBaiduMusic": false,
        "isPaid": false,
        "duration": 1672,
        "src": "http://audio.xmcdn.com/group31/M03/21/9D/wKgJX1mBlBPiwvG6AM5vRiNgPD4128.m4a",
        "hasBuy": true,
        "albumIsSample": false,
        "sampleDuration": 0,
        "updateTime": "2月前",
        "createTime": "1年前",
        "isLike": false,
        "isCopyright": true,
        "firstPlayStatus": true
      },
      {
        "index": 25,
        "trackId": 45982923,
        "trackName": "《麻雀也能下鹅蛋》郭德纲 于谦",
        "trackUrl": "/xiangsheng/9723091/45982923",
        "trackCoverPath": "//imagev2.xmcdn.com/group31/M07/0E/5B/wKgJX1mAQg2SWaYDAAAw0CICWi8444.jpg",
        "albumId": 9723091,
        "albumName": "郭德纲21年相声精选",
        "albumUrl": "/xiangsheng/9723091/",
        "anchorId": 1000202,
        "canPlay": true,
        "isBaiduMusic": false,
        "isPaid": false,
        "duration": 4939,
        "src": "http://aod.tx.xmcdn.com/group31/M06/21/BF/wKgJSVmBlCKi9OTyAmGItLSD8CQ228.m4a",
        "hasBuy": true,
        "albumIsSample": false,
        "sampleDuration": 0,
        "updateTime": "9月前",
        "createTime": "1年前",
        "isLike": false,
        "isCopyright": true,
        "firstPlayStatus": true
      },
      {
        "index": 26,
        "trackId": 45982937,
        "trackName": "《满汉全席》郭德纲 于谦",
        "trackUrl": "/xiangsheng/9723091/45982937",
        "trackCoverPath": "//imagev2.xmcdn.com/group31/M07/0E/5B/wKgJX1mAQg2SWaYDAAAw0CICWi8444.jpg",
        "albumId": 9723091,
        "albumName": "郭德纲21年相声精选",
        "albumUrl": "/xiangsheng/9723091/",
        "anchorId": 1000202,
        "canPlay": true,
        "isBaiduMusic": false,
        "isPaid": false,
        "duration": 4114,
        "src": "http://aod.tx.xmcdn.com/group31/M03/21/9D/wKgJX1mBlCSQa6uzAfuvPbRZJ1M139.m4a",
        "hasBuy": true,
        "albumIsSample": false,
        "sampleDuration": 0,
        "updateTime": "2月前",
        "createTime": "1年前",
        "isLike": false,
        "isCopyright": true,
        "firstPlayStatus": true
      },
      {
        "index": 27,
        "trackId": 45982943,
        "trackName": "《死鬼快进来》郭德纲 于谦",
        "trackUrl": "/xiangsheng/9723091/45982943",
        "trackCoverPath": "//imagev2.xmcdn.com/group31/M07/0E/5B/wKgJX1mAQg2SWaYDAAAw0CICWi8444.jpg",
        "albumId": 9723091,
        "albumName": "郭德纲21年相声精选",
        "albumUrl": "/xiangsheng/9723091/",
        "anchorId": 1000202,
        "canPlay": true,
        "isBaiduMusic": false,
        "isPaid": false,
        "duration": 1846,
        "src": "http://aod.tx.xmcdn.com/group30/M00/3F/4E/wKgJXlmBlCujUx2aAOPdpFhePAw883.m4a",
        "hasBuy": true,
        "albumIsSample": false,
        "sampleDuration": 0,
        "updateTime": "7月前",
        "createTime": "1年前",
        "isLike": false,
        "isCopyright": true,
        "firstPlayStatus": true
      },
      {
        "index": 28,
        "trackId": 45983013,
        "trackName": "《跳大神》郭德纲 于谦",
        "trackUrl": "/xiangsheng/9723091/45983013",
        "trackCoverPath": "//imagev2.xmcdn.com/group31/M07/0E/5B/wKgJX1mAQg2SWaYDAAAw0CICWi8444.jpg",
        "albumId": 9723091,
        "albumName": "郭德纲21年相声精选",
        "albumUrl": "/xiangsheng/9723091/",
        "anchorId": 1000202,
        "canPlay": true,
        "isBaiduMusic": false,
        "isPaid": false,
        "duration": 1854,
        "src": "http://aod.tx.xmcdn.com/group30/M00/3F/54/wKgJXlmBlEnh5I6mAOTUEGiSPJI859.m4a",
        "hasBuy": true,
        "albumIsSample": false,
        "sampleDuration": 0,
        "updateTime": "1年前",
        "createTime": "1年前",
        "isLike": false,
        "isCopyright": true,
        "firstPlayStatus": true
      },
      {
        "index": 29,
        "trackId": 45983017,
        "trackName": "《贴身大丫鬟》郭德纲 于谦",
        "trackUrl": "/xiangsheng/9723091/45983017",
        "trackCoverPath": "//imagev2.xmcdn.com/group31/M07/0E/5B/wKgJX1mAQg2SWaYDAAAw0CICWi8444.jpg",
        "albumId": 9723091,
        "albumName": "郭德纲21年相声精选",
        "albumUrl": "/xiangsheng/9723091/",
        "anchorId": 1000202,
        "canPlay": true,
        "isBaiduMusic": false,
        "isPaid": false,
        "duration": 1003,
        "src": "http://aod.tx.xmcdn.com/group30/M00/3F/57/wKgJXlmBlErAGEXKAHvTTbxsc4g608.m4a",
        "hasBuy": true,
        "albumIsSample": false,
        "sampleDuration": 0,
        "updateTime": "1年前",
        "createTime": "1年前",
        "isLike": false,
        "isCopyright": true,
        "firstPlayStatus": true
      },
      {
        "index": 30,
        "trackId": 45983022,
        "trackName": "《歪唱太平歌词》郭德纲 郭麒麟",
        "trackUrl": "/xiangsheng/9723091/45983022",
        "trackCoverPath": "//imagev2.xmcdn.com/group31/M07/0E/5B/wKgJX1mAQg2SWaYDAAAw0CICWi8444.jpg",
        "albumId": 9723091,
        "albumName": "郭德纲21年相声精选",
        "albumUrl": "/xiangsheng/9723091/",
        "anchorId": 1000202,
        "canPlay": true,
        "isBaiduMusic": false,
        "isPaid": false,
        "duration": 1575,
        "src": "http://audio.xmcdn.com/group31/M0B/21/C5/wKgJSVmBlFiwZCT1AMJleMtPYYU665.m4a",
        "hasBuy": true,
        "albumIsSample": false,
        "sampleDuration": 0,
        "updateTime": "1年前",
        "createTime": "1年前",
        "isLike": false,
        "isCopyright": true,
        "firstPlayStatus": true
      }
    ],
    "hasMore": true
  }
}
